photfun/__init__.py
photfun/run_photfun.py
photfun/daophot_opt/__init__.py
photfun/daophot_opt/opt_dict.py
photfun/daophot_opt/opt_help.py
photfun/daophot_wrap/__init__.py
photfun/daophot_wrap/allframe.py
photfun/daophot_wrap/allstar.py
photfun/daophot_wrap/create_master.py
photfun/daophot_wrap/create_psf.py
photfun/daophot_wrap/daomaster.py
photfun/daophot_wrap/daomatch.py
photfun/daophot_wrap/docker_handler.py
photfun/daophot_wrap/find.py
photfun/daophot_wrap/phot.py
photfun/daophot_wrap/pick.py
photfun/daophot_wrap/psf_preview.py
photfun/daophot_wrap/sub_fits.py
photfun/daophot_wrap/tools/fake.fits
photfun/daophot_wrap/tools/fake.lst
photfun/misc_tools/__init__.py
photfun/misc_tools/check_file.py
photfun/misc_tools/copy_file_noreplace.py
photfun/misc_tools/cube_slicer.py
photfun/misc_tools/daophot_pbar.py
photfun/misc_tools/move_file_noreplace.py
photfun/misc_tools/samp_client.py
photfun/misc_tools/spectra_compiler.py
photfun/misc_tools/temp_mkdir.py
photfun/misc_tools/testing.py
photfun/photfun_classes/__init__.py
photfun/photfun_classes/phot_file.py
photfun/photfun_classes/phot_fits.py
photfun/photfun_classes/phot_fun.py
photfun/photfun_classes/phot_psf.py
photfun/photfun_classes/phot_table.py
photfun/photfun_gui/__init__.py
photfun/photfun_gui/app.py
photfun/photfun_gui/server.py
photfun/photfun_gui/gui_custom/__init__.py
photfun/photfun_gui/gui_custom/input_local_file.py
photfun/photfun_gui/gui_custom/nav_panel_DAOPHOT.py
photfun/photfun_gui/gui_custom/nav_panel_EXPORT.py
photfun/photfun_gui/gui_custom/nav_panel_GRIDSEARCH.py
photfun/photfun_gui/gui_custom/nav_panel_IMAGE.py
photfun/photfun_gui/gui_custom/nav_panel_LOGS.py
photfun/photfun_gui/gui_custom/nav_panel_PHOTCUBE.py
photfun/photfun_gui/gui_custom/nav_panel_PIPELINES.py
photfun/photfun_gui/gui_custom/nav_panel_PSF.py
photfun/photfun_gui/gui_custom/nav_panel_SELECTION.py
photfun/photfun_gui/gui_custom/nav_panel_TABLE.py
photfun/photfun_gui/gui_custom/nav_table_sideview.py
photfun-0.1.15.dist-info/licenses/LICENSE
photfun-0.1.15.dist-info/METADATA
photfun-0.1.15.dist-info/WHEEL
photfun-0.1.15.dist-info/entry_points.txt
photfun-0.1.15.dist-info/top_level.txt
photfun-0.1.15.dist-info/RECORD
