Metadata-Version: 2.4
Name: photfun
Version: 0.1.15
Summary: PHOTfun is an interactive adaptation of the DAOPHOT 
Home-page: https://github.com/ciquezada/photfun
Author: Carlos Quezada
License: MIT
Keywords: daophot,astronomical,python
Requires-Python: >=3.11
License-File: LICENSE
Requires-Dist: astropy==7.0.1
Requires-Dist: faicons==0.2.2
Requires-Dist: imageio==2.37.0
Requires-Dist: joblib==1.4.2
Requires-Dist: matplotlib==3.10.1
Requires-Dist: nest_asyncio==1.6.0
Requires-Dist: numpy==2.2.5
Requires-Dist: pandas==2.2.3
Requires-Dist: Pillow==11.3
Requires-Dist: scipy==1.15.2
Requires-Dist: shiny==1.4.0
Requires-Dist: tqdm==4.67.1
Requires-Dist: docker
Requires-Dist: psutil==7.0.0
Requires-Dist: scikit-optimize
Dynamic: author
Dynamic: description
Dynamic: description-content-type
Dynamic: home-page
Dynamic: keywords
Dynamic: license
Dynamic: license-file
Dynamic: requires-dist
Dynamic: requires-python
Dynamic: summary
